ansible_targetnode_setup/__init__.py
ansible_targetnode_setup/controller.py
ansible_ctargetnode_setup-0.2.dist-info/LICENSE
ansible_ctargetnode_setup-0.2.dist-info/METADATA
ansible_ctargetnode_setup-0.2.dist-info/WHEEL
ansible_ctargetnode_setup-0.2.dist-info/entry_points.txt
ansible_ctargetnode_setup-0.2.dist-info/top_level.txt
ansible_ctargetnode_setup-0.2.dist-info/RECORD
