Metadata-Version: 2.1
Name: ansible-ctargetnode-setup
Version: 0.2
Summary: A Python package to automate Ansible TargetNode installation and configuration.
Home-page: UNKNOWN
Author: Mohammad Noorain
Author-email: your-email@example.com
License: UNKNOWN
Platform: UNKNOWN
Classifier: Programming Language :: Python :: 3
Classifier: License :: OSI Approved :: MIT License
Classifier: Operating System :: Unix
License-File: LICENSE
